setup.py
unacorn_api/__init__.py
unacorn_api/unacorn_api.py
unacorn_api.egg-info/PKG-INFO
unacorn_api.egg-info/SOURCES.txt
unacorn_api.egg-info/dependency_links.txt
unacorn_api.egg-info/top_level.txt