Metadata-Version: 2.1
Name: unacorn-api
Version: 0.1
Summary: Unacorn API Pulls andRequests
Author: Nicholas Ramdin
Author-email: nicholas.ramdin@torch.ai
